bibliocommons/__init__.py
bibliocommons-2025.3.dist-info/WHEEL
bibliocommons-2025.3.dist-info/METADATA
bibliocommons-2025.3.dist-info/RECORD
