Metadata-Version: 2.4
Name: bibliocommons
Version: 2025.3
Summary: Python client library to interface with BiblioCommons library systems
Author: William Jackson
Author-email: William Jackson <william@subtlecoolness.com>
License-Expression: MIT
Classifier: Programming Language :: Python :: 3
Classifier: Operating System :: OS Independent
Requires-Dist: cssselect>=1.3.0
Requires-Dist: httpx>=0.28.1
Requires-Dist: lxml>=6.0.0
Requires-Python: >=3.9
Project-URL: Changes, https://github.com/williamjacksn/python-bibliocommons/releases
Project-URL: Homepage, https://github.com/williamjacksn/python-bibliocommons
Project-URL: Issues, https://github.com/williamjacksn/python-bibliocommons/issues
